lib_1/__init__.py
lib_1/info.py
lib_1-1.0.3.dist-info/LICENSE
lib_1-1.0.3.dist-info/METADATA
lib_1-1.0.3.dist-info/WHEEL
lib_1-1.0.3.dist-info/entry_points.txt
lib_1-1.0.3.dist-info/top_level.txt
lib_1-1.0.3.dist-info/RECORD
