Metadata-Version: 2.1
Name: lib-1
Version: 1.0.3
Summary: information about author
Home-page: https://github.com/SurendraKumawat23
Author: Surendra Kumawat
Author-email: surendrakumawatp@gmail.com
License: MIT
Platform: UNKNOWN
Classifier: License :: OSI Approved :: MIT License
Classifier: Programming Language :: Python :: 3
Classifier: Programming Language :: Python :: 3.7
